radicale_auth_odoo/__init__.py
radicale_auth_odoo-1.0.0.0.dist-info/DESCRIPTION.rst
radicale_auth_odoo-1.0.0.0.dist-info/METADATA
radicale_auth_odoo-1.0.0.0.dist-info/RECORD
radicale_auth_odoo-1.0.0.0.dist-info/WHEEL
radicale_auth_odoo-1.0.0.0.dist-info/metadata.json
radicale_auth_odoo-1.0.0.0.dist-info/top_level.txt
