Metadata-Version: 2.0
Name: radicale-auth-odoo
Version: 1.0.0.0
Summary: Odoo Authenticaiton Plugin for Radicale 2
Home-page: https://git.hugorodrigues.net/hugorodrigues/radicale_auth_odoo
Author: Hugo Rodrigues
Author-email: me@hugorodrigues.net
License: BSD-3-Clause
Platform: UNKNOWN
Classifier: Development Status :: 5 - Production/Stable
Classifier: License :: OSI Approved :: BSD License
Classifier: Natural Language :: English
Classifier: Programming Language :: Python :: 3 :: Only
Requires-Dist: radicale (>=2.0)
